pygsheets/__init__.py
pygsheets/address.py
pygsheets/authorization.py
pygsheets/cell.py
pygsheets/chart.py
pygsheets/client.py
pygsheets/custom_types.py
pygsheets/datarange.py
pygsheets/developer_metadata.py
pygsheets/drive.py
pygsheets/exceptions.py
pygsheets/sheet.py
pygsheets/spreadsheet.py
pygsheets/utils.py
pygsheets/worksheet.py
pygsheets/data/drive_discovery.json
pygsheets/data/sheets_discovery.json
pygsheets-2.0.4.dist-info/LICENSE.txt
pygsheets-2.0.4.dist-info/METADATA
pygsheets-2.0.4.dist-info/WHEEL
pygsheets-2.0.4.dist-info/top_level.txt
pygsheets-2.0.4.dist-info/RECORD
